<?xml version="1.0" encoding="utf-8"?>
<abapGit version="v1.0.0" serializer="LCL_OBJECT_VIEW" serializer_version="v1.0.0">
 <asx:abap xmlns:asx="http://www.sap.com/abapxml" version="1.0">
  <asx:values>
   <DD25V>
    <VIEWNAME>ZCMA_VIEW</VIEWNAME>
    <AS4LOCAL>A</AS4LOCAL>
    <AGGTYPE>V</AGGTYPE>
    <ROOTTAB>ZCMA_EMPLOYEE</ROOTTAB>
    <VIEWCLASS>D</VIEWCLASS>
    <VIEWGRANT>R</VIEWGRANT>
   </DD25V>
   <DD26V_TABLE>
    <DD26V>
     <VIEWNAME>ZCMA_VIEW</VIEWNAME>
     <TABNAME>ZCMA_EMPLOYEE</TABNAME>
     <TABPOS>0001</TABPOS>
     <FORTABNAME>ZCMA_EMPLOYEE</FORTABNAME>
    </DD26V>
    <DD26V>
     <VIEWNAME>ZCMA_VIEW</VIEWNAME>
     <TABNAME>ZCMA_DEPARTMENT</TABNAME>
     <TABPOS>0002</TABPOS>
    </DD26V>
   </DD26V_TABLE>
   <DD27P_TABLE>
    <DD27P>
     <VIEWNAME>ZCMA_VIEW</VIEWNAME>
     <OBJPOS>0001</OBJPOS>
     <VIEWFIELD>DEPARTAMENTO</VIEWFIELD>
     <TABNAME>ZCMA_DEPARTMENT</TABNAME>
     <FIELDNAME>NAME</FIELDNAME>
     <KEYFLAG>X</KEYFLAG>
     <ROLLNAME>ZCMA_DEPARTMENT_NAME</ROLLNAME>
     <ROLLNAMEVI>ZCMA_DEPARTMENT_NAME</ROLLNAMEVI>
    </DD27P>
    <DD27P>
     <VIEWNAME>ZCMA_VIEW</VIEWNAME>
     <OBJPOS>0002</OBJPOS>
     <VIEWFIELD>FUNCIONARIO</VIEWFIELD>
     <TABNAME>ZCMA_EMPLOYEE</TABNAME>
     <FIELDNAME>NAME</FIELDNAME>
     <KEYFLAG>X</KEYFLAG>
     <ROLLNAME>ZCMA_EMPLOYEE_NAME</ROLLNAME>
     <ROLLNAMEVI>ZCMA_EMPLOYEE_NAME</ROLLNAMEVI>
    </DD27P>
   </DD27P_TABLE>
   <DD28J_TABLE>
    <DD28J>
     <VIEWNAME>ZCMA_VIEW</VIEWNAME>
     <LTAB>ZCMA_EMPLOYEE</LTAB>
     <LFIELD>DEPARTMENT_ID</LFIELD>
     <OPERATOR>EQ</OPERATOR>
     <RTAB>ZCMA_DEPARTMENT</RTAB>
     <RFIELD>DEPARTMENT_ID</RFIELD>
     <SOURCE>S</SOURCE>
    </DD28J>
   </DD28J_TABLE>
  </asx:values>
 </asx:abap>
</abapGit>
